{
  "_class": "group",
  "do_objectID": "271A06C6-EB5D-449D-A0ED-28346D8C87A7",
  "exportOptions": {
    "_class": "exportOptions",
    "exportFormats": [
    ],
    "includedLayerIds": [
    ],
    "layerOptions": 0,
    "shouldTrim": false
  },
  "frame": {
    "_class": "rect",
    "constrainProportions": true,
    "height": 25,
    "width": 19,
    "x": 0,
    "y": 0
  },
  "hasClickThrough": false,
  "isFlippedHorizontal": false,
  "isFlippedVertical": false,
  "isLocked": false,
  "isVisible": true,
  "layerListExpandedType": 0,
  "layers": [
    {
      "class": "group",
      "id": "423B798F-A954-4B41-B444-E432A7287DAF"
    }
  ],
  "name": "cursorhand",
  "nameIsFixed": false,
  "originalObjectID": "271A06C6-EB5D-449D-A0ED-28346D8C87A7",
  "resizingConstraint": 63,
  "resizingType": 0,
  "rotation": 0,
  "shouldBreakMaskChain": false,
  "style": {
    "_class": "style",
    "endDecorationType": 0,
    "miterLimit": 10,
    "startDecorationType": 0
  },
  "userInfo": {
    "com.animaapp.stc-sketch-plugin": {
      "kModelPropertiesKey": {
        "constraints": {
          "aspectRatio": {
            "constant": 25,
            "enabled": 1,
            "modelID": "constraint_92f11635-17e8-42dd-b944-fc6c9adff2f9",
            "model_class": "ADModelConstraint",
            "model_version": 0.1,
            "multiplier": 19
          },
          "automatic": 1,
          "modelID": "viewConstraints_722523eb-4935-4800-8862-497a2f75d4de",
          "model_class": "ADModelViewConstraints",
          "model_version": 0.1,
          "scaleFactor": 1
        }
      }
    }
  }
}