{
  "_class": "group",
  "do_objectID": "25F5CB02-D8F7-4330-B0D2-5C004179A4F2",
  "exportOptions": {
    "_class": "exportOptions",
    "exportFormats": [
    ],
    "includedLayerIds": [
    ],
    "layerOptions": 0,
    "shouldTrim": false
  },
  "frame": {
    "_class": "rect",
    "constrainProportions": false,
    "height": 24,
    "width": 252,
    "x": 0,
    "y": 32
  },
  "hasClickThrough": false,
  "isFlippedHorizontal": false,
  "isFlippedVertical": false,
  "isLocked": false,
  "isVisible": true,
  "layerListExpandedType": 0,
  "layers": [
    {
      "class": "text",
      "id": "9D927905-C626-49DE-AAD7-992956DAA72C"
    },
    {
      "class": "symbolInstance",
      "id": "03D3BC12-C791-486F-B38F-C212954C579A"
    }
  ],
  "name": "Group 4 Copy 5",
  "nameIsFixed": false,
  "resizingConstraint": 63,
  "resizingType": 0,
  "rotation": 0,
  "shouldBreakMaskChain": false,
  "style": {
    "_class": "style",
    "endDecorationType": 0,
    "miterLimit": 10,
    "startDecorationType": 0
  },
  "userInfo": {
    "com.animaapp.stc-sketch-plugin": {
      "kModelPropertiesKey": {
      }
    }
  }
}