{
  "_class": "group",
  "do_objectID": "840F751B-0E12-47A4-86B8-953C8066D545",
  "exportOptions": {
    "_class": "exportOptions",
    "exportFormats": [
    ],
    "includedLayerIds": [
    ],
    "layerOptions": 0,
    "shouldTrim": false
  },
  "frame": {
    "_class": "rect",
    "constrainProportions": false,
    "height": 40,
    "width": 378,
    "x": 0,
    "y": 27
  },
  "hasClickThrough": false,
  "isFlippedHorizontal": false,
  "isFlippedVertical": false,
  "isLocked": false,
  "isVisible": true,
  "layerListExpandedType": 0,
  "layers": [
    {
      "class": "shapeGroup",
      "id": "97F52F80-142D-4FFC-A9E4-CF73A7B2D59A"
    },
    {
      "class": "text",
      "id": "25A24F72-CFBF-4415-83DA-378CA54266BC"
    },
    {
      "class": "symbolInstance",
      "id": "E974F038-C159-4C95-9E1C-B301D3D3BBC6"
    }
  ],
  "name": "Field",
  "nameIsFixed": true,
  "resizingConstraint": 63,
  "resizingType": 0,
  "rotation": 0,
  "shouldBreakMaskChain": false,
  "style": {
    "_class": "style",
    "endDecorationType": 0,
    "miterLimit": 10,
    "startDecorationType": 0
  },
  "userInfo": {
    "com.animaapp.stc-sketch-plugin": {
      "kModelPropertiesKey": {
      }
    }
  }
}